langchain_iceberg/__init__.py
langchain_iceberg/exceptions.py
langchain_iceberg/toolkit.py
langchain_iceberg/version.py
langchain_iceberg/loaders/__init__.py
langchain_iceberg/loaders/semantic_loader.py
langchain_iceberg/tools/__init__.py
langchain_iceberg/tools/base.py
langchain_iceberg/tools/catalog_tools.py
langchain_iceberg/tools/query_planner_tool.py
langchain_iceberg/tools/query_tools.py
langchain_iceberg/tools/semantic_tools.py
langchain_iceberg/tools/snapshot_tools.py
langchain_iceberg/utils/__init__.py
langchain_iceberg/utils/date_parser.py
langchain_iceberg/utils/filters.py
langchain_iceberg/utils/formatters.py
langchain_iceberg/utils/validators.py
langchain_iceberg-0.1.1.dist-info/licenses/LICENSE
langchain_iceberg-0.1.1.dist-info/METADATA
langchain_iceberg-0.1.1.dist-info/WHEEL
langchain_iceberg-0.1.1.dist-info/top_level.txt
langchain_iceberg-0.1.1.dist-info/RECORD
