Metadata-Version: 2.4
Name: langchain-iceberg
Version: 0.1.1
Summary: LangChain integration for Apache Iceberg with native PyIceberg API support
Author: Vipin Kataria
License-Expression: Apache-2.0
Project-URL: Homepage, https://github.com/langchain-ai/langchain-iceberg
Project-URL: Documentation, https://github.com/langchain-ai/langchain-iceberg#readme
Project-URL: Repository, https://github.com/langchain-ai/langchain-iceberg
Project-URL: Issues, https://github.com/langchain-ai/langchain-iceberg/issues
Keywords: langchain,iceberg,data-lake,sql,ai,llm
Classifier: Development Status :: 3 - Alpha
Classifier: Intended Audience :: Developers
Classifier: Programming Language :: Python :: 3
Classifier: Programming Language :: Python :: 3.10
Classifier: Programming Language :: Python :: 3.11
Classifier: Programming Language :: Python :: 3.12
Classifier: Topic :: Software Development :: Libraries :: Python Modules
Classifier: Topic :: Database
Classifier: Topic :: Scientific/Engineering :: Artificial Intelligence
Requires-Python: >=3.10
License-File: LICENSE
Requires-Dist: langchain-core>=0.3.0
Requires-Dist: pyiceberg>=0.7.0
Requires-Dist: pydantic>=2.0
Requires-Dist: pandas>=2.0
Requires-Dist: pyarrow>=14.0
Requires-Dist: pyyaml>=6.0
Provides-Extra: semantic
Requires-Dist: pyyaml>=6.0; extra == "semantic"
Provides-Extra: redis
Requires-Dist: redis>=5.0; extra == "redis"
Provides-Extra: dev
Requires-Dist: langchain-tests>=0.0.1; extra == "dev"
Requires-Dist: pytest>=7.4.0; extra == "dev"
Requires-Dist: pytest-cov>=4.1.0; extra == "dev"
Requires-Dist: pytest-asyncio>=0.21.0; extra == "dev"
Requires-Dist: black>=23.0.0; extra == "dev"
Requires-Dist: ruff>=0.1.0; extra == "dev"
Requires-Dist: mypy>=1.5.0; extra == "dev"
Requires-Dist: types-pyyaml>=6.0; extra == "dev"
Provides-Extra: test
Requires-Dist: langchain-tests>=0.0.1; extra == "test"
Requires-Dist: pytest>=7.4.0; extra == "test"
Requires-Dist: pytest-cov>=4.1.0; extra == "test"
Requires-Dist: pytest-asyncio>=0.21.0; extra == "test"
Requires-Dist: pytest-socket>=0.7.0; extra == "test"
Provides-Extra: test-integration
Requires-Dist: pytest-xdist>=3.0.0; extra == "test-integration"
Dynamic: license-file
